files/__init__.py
files/bit.py
files/bit_fuzz.py
files/bno.py
files/cnf.py
files/dl2.py
files/http_object.py
files/hubby.py
files/lib.py
files/message_object.py
files/mp3Cutter.py
files/omm_file_parser.py
files/online_omm_parser.py
files/ono.py
files/onoObject.py
files/search_srt.py
files/setup.py
files/sh.py
files/srt_cli.py
files/srt_keyword_parser.py
files/srt_search_function.py
files/videomachine_operator.py
files/yn.py
files/yno.py
files/yota.py
files/yota_fuzz.py
files/yss_parser.py
files/yt_stepper.py
mb-0.9.2.1.dist-info/LICENSE
mb-0.9.2.1.dist-info/METADATA
mb-0.9.2.1.dist-info/WHEEL
mb-0.9.2.1.dist-info/top_level.txt
mb-0.9.2.1.dist-info/RECORD
