Metadata-Version: 2.1
Name: mb
Version: 0.9.2.1
Summary: UNKNOWN
Home-page: UNKNOWN
Author: David Mekonnen Rønn
Author-email: gh@v1d.dk
License: UNKNOWN
Platform: UNKNOWN
Classifier: Programming Language :: Python :: 3
Classifier: Operating System :: OS Independent
License-File: LICENSE
Requires-Dist: youtube-dl
Requires-Dist: pydub
Requires-Dist: sh
